{
	"layer_jumpingpuzzle_icon": {
		"type": "jumpingpuzzle",
		"data": {
			"15": [
				{
					"coord": [45966, 30066],
					"name": "Demongrub Pits (jumping puzzle)"
				}
			],
			"17": [
				{
					"coord": [47105, 26040],
					"name": "Fawcett's Bounty"
				}
			],
			"19": [
				{
					"coord": [61209, 31900],
					"name": "Loreclaw Expanse (jumping puzzle)"
				}
			],
			"20": [
				{
					"coord": [63867, 31585],
					"name": "Behem Gauntlet (jumping puzzle)"
				},
				{
					"coord": [63749, 28842],
					"name": "Craze's Folly (jumping puzzle)"
				}
			],
			"21": [
				{
					"coord": [61729, 33222],
					"name": "Branded Mine"
				}
			],
			"22": [
				{
					"coord": [58757, 27102],
					"name": "Pig Iron Quarry"
				}
			],
			"23": [
				{
					"coord": [45552, 32310],
					"name": "The Collapsed Observatory"
				}
			],
			"24": [
				{
					"coord": [49286, 30596],
					"name": "Swashbuckler's Cove"
				},
				{
					"coord": [48151, 30661],
					"name": "Not So Secret"
				}
			],
			"25": [
				{
					"coord": [60158, 29456],
					"name": "Chaos Crystal Cavern"
				}
			],
			"26": [
				{
					"coord": [52460, 34367],
					"name": "Tribulation Caverns"
				},
				{
					"coord": [52588, 34349],
					"name": "Tribulation Rift Scaffolding"
				}
			],
			"27": [
				{
					"coord": [50856, 33507],
					"name": "Griffonrook Run (jumping puzzle)"
				}
			],
			"28": [
				{
					"coord": [54811, 30007],
					"name": "Shamans Rookery"
				}
			],
			"29": [
				{
					"coord": [53430, 37590],
					"name": "Coddler's Cove"
				},
				{
					"coord": [53825, 35143],
					"name": "Only Zuhl"
				}
			],
			"30": [
				{
					"coord": [54849, 25525],
					"name": "Shattered Ice Ruins"
				}
			],
			"31": [
				{
					"coord": [54296, 28630],
					"name": "King Jalis's Refuge (jumping puzzle)"
				}
			],
			"32": [
				{
					"coord": [58952, 29457],
					"name": "Crimson Plateau"
				},
				{
					"coord": [57901, 28631],
					"name": "Grendich Gamble"
				},
				{
					"coord": [58299, 29788],
					"name": "Wall Breach Blitz"
				}
			],
			"34": [
				{
					"coord": [43677, 35497],
					"name": "Dark Reverie"
				},
				{
					"coord": [43791, 35738],
					"name": "Morgan's Leap"
				},
				{
					"coord": [42301, 34988],
					"name": "Spekks's Laboratory"
				},
				{
					"coord": [43394, 36407],
					"name": "Spelunker's Delve"
				}
			],
			"35": [
				{
					"coord": [42003, 35329],
					"name": "Goemm's Lab"
				}
			],
			"39": [
				{
					"coord": [50722, 38019],
					"name": "Conundrum Cubed"
				},
				{
					"coord": [54243, 38232],
					"name": "Hidden Garden"
				}
			],
			"50": [
				{
					"coord": [49377, 31509],
					"name": "Troll's Revenge"
				},
				{
					"coord": [50284, 31043],
					"name": "Urmaug's Secret"
				},
				{
					"coord": [50120, 32011],
					"name": "Weyandt's Revenge"
				}
			],
			"51": [
				{
					"coord": [49118, 40851],
					"name": "Vizier's Tower"
				}
			],
			"53": [
				{
					"coord": [50343, 38362],
					"name": "Hexfoundry Unhinged"
				}
			],
			"62": [
				{
					"coord": [43843, 45383],
					"name": "Buried Archives"
				}
			],
			"65": [
				{
					"coord": [46380, 41193],
					"name": "Antre of Adjournment"
				},
				{
					"coord": [46388, 41440],
					"name": "Scavenger's Chasm"
				}
			],
			"73": [
				{
					"coord": [48488, 32808],
					"name": "Professor Portmatt's Lab"
				}
			],
			"873": [
				{
					"coord": [45545, 35760],
					"name": "Skipping Stones"
				},
				{
					"coord": [46651, 36802],
					"name": "Under New Management"
				}
			],
			"899": [
				{
					"coord": [44531, 30026],
					"name": "Obsidian Sanctum"
				}
			],
			"988": [
				{
					"coord": [38103, 32974],
					"name": "Prospect Valley Crash Site"
				}
			],
			"1015": [
				{
					"coord": [38032, 31354],
					"name": "Drydock Scratch"
				}
			],
			"1175": [
				{
					"coord": [38380, 45486],
					"name": "Skip up the Volcano"
				}
			],
			"1185": [
				{
					"coord": [45188, 25652],
					"name": "Noran's Safe Room"
				}
			],
			"1195": [
				{
					"coord": [36618, 41640],
					"name": "Searing Ascent (jumping puzzle)"
				}
			],
			"1203": [
				{
					"coord": [49613, 41882],
					"name": "Abaddon's Ascent"
				}
			],
			"1330": [
				{
					"coord": [61590, 17856],
					"name": "Gauntlet of the Khan-Ur"
				}
			]
		}
	}
}
